my_ai_sdk/__init__.py
my_ai_sdk/client.py
firsttest_sdk-0.2.0.dist-info/METADATA
firsttest_sdk-0.2.0.dist-info/WHEEL
firsttest_sdk-0.2.0.dist-info/top_level.txt
firsttest_sdk-0.2.0.dist-info/RECORD
